streamlit_img_label_ita/__init__.py
streamlit_img_label_ita/annotation.py
streamlit_img_label_ita/manage.py
streamlit_img_label_ita/frontend/build/.DS_Store
streamlit_img_label_ita/frontend/build/asset-manifest.json
streamlit_img_label_ita/frontend/build/bootstrap.min.css
streamlit_img_label_ita/frontend/build/index.html
streamlit_img_label_ita/frontend/build/precache-manifest.b5513ea1aa30f2a517dcf8a664ec6a82.js
streamlit_img_label_ita/frontend/build/service-worker.js
streamlit_img_label_ita/frontend/build/static/.DS_Store
streamlit_img_label_ita/frontend/build/static/css/main.00623a57.chunk.css
streamlit_img_label_ita/frontend/build/static/css/main.00623a57.chunk.css.map
streamlit_img_label_ita/frontend/build/static/js/2.b19543fd.chunk.js
streamlit_img_label_ita/frontend/build/static/js/2.b19543fd.chunk.js.LICENSE.txt
streamlit_img_label_ita/frontend/build/static/js/2.b19543fd.chunk.js.map
streamlit_img_label_ita/frontend/build/static/js/main.25f4a86d.chunk.js
streamlit_img_label_ita/frontend/build/static/js/main.25f4a86d.chunk.js.map
streamlit_img_label_ita/frontend/build/static/js/runtime-main.4a6ba311.js
streamlit_img_label_ita/frontend/build/static/js/runtime-main.4a6ba311.js.map
streamlit_img_label_ita-0.1.18.dist-info/LICENSE
streamlit_img_label_ita-0.1.18.dist-info/METADATA
streamlit_img_label_ita-0.1.18.dist-info/WHEEL
streamlit_img_label_ita-0.1.18.dist-info/top_level.txt
streamlit_img_label_ita-0.1.18.dist-info/RECORD
