Metadata-Version: 2.1
Name: streamlit-img-label-ita
Version: 0.1.18
Summary: Streamlit Image Annotation
Home-page: https://github.com/lit26/streamlit-img-label
Author: Tianning Li and contributors Alessandro Ciciarelli
Author-email: ltianningli@gmail.com
License: UNKNOWN
Platform: UNKNOWN
Requires-Python: >=3.6
License-File: LICENSE
Requires-Dist: streamlit (>=0.63)
